[
  {"question": "How do I implement a binary search tree in Python?", "intent": "software_engineering"},
  {"question": "What's the difference between OOP and functional programming?", "intent": "software_engineering"},
  {"question": "How can I optimize database queries for better performance?", "intent": "software_engineering"},
  {"question": "What are design patterns and why should I use them?", "intent": "software_engineering"},
  {"question": "How do I handle memory leaks in my application?", "intent": "software_engineering"},
  {"question": "What's the best way to structure a REST API?", "intent": "software_engineering"},
  {"question": "How do I implement unit testing in my codebase?", "intent": "software_engineering"},
  {"question": "What's the difference between synchronous and asynchronous programming?", "intent": "software_engineering"},
  {"question": "How can I improve code maintainability?", "intent": "software_engineering"},
  {"question": "What are microservices and when should I use them?", "intent": "software_engineering"},
  {"question": "How do I debug a segmentation fault?", "intent": "software_engineering"},
  {"question": "What's the difference between stack and heap memory?", "intent": "software_engineering"},
  {"question": "How do I implement caching in my application?", "intent": "software_engineering"},
  {"question": "What are SOLID principles in software design?", "intent": "software_engineering"},
  {"question": "How can I refactor legacy code safely?", "intent": "software_engineering"},

  {"question": "How do I deploy an application on AWS?", "intent": "cloud"},
  {"question": "What's the difference between S3 and EBS?", "intent": "cloud"},
  {"question": "How can I reduce my cloud computing costs?", "intent": "cloud"},
  {"question": "What are the benefits of serverless architecture?", "intent": "cloud"},
  {"question": "How do I set up auto-scaling on Azure?", "intent": "cloud"},
  {"question": "What's the difference between IaaS, PaaS, and SaaS?", "intent": "cloud"},
  {"question": "How can I migrate my on-premise database to the cloud?", "intent": "cloud"},
  {"question": "What are cloud security best practices?", "intent": "cloud"},
  {"question": "How do I implement disaster recovery in the cloud?", "intent": "cloud"},
  {"question": "What's the difference between vertical and horizontal scaling?", "intent": "cloud"},
  {"question": "How can I monitor cloud resource usage?", "intent": "cloud"},
  {"question": "What are availability zones in cloud computing?", "intent": "cloud"},
  {"question": "How do I set up a VPN for cloud resources?", "intent": "cloud"},
  {"question": "What's the difference between public and private cloud?", "intent": "cloud"},
  {"question": "How can I optimize cloud storage costs?", "intent": "cloud"},

  {"question": "What's the difference between CI and CD?", "intent": "devops"},
  {"question": "How do I set up a Jenkins pipeline?", "intent": "devops"},
  {"question": "What are the benefits of using Docker containers?", "intent": "devops"},
  {"question": "How can I implement infrastructure as code?", "intent": "devops"},
  {"question": "What's the purpose of Kubernetes orchestration?", "intent": "devops"},
  {"question": "How do I automate deployment processes?", "intent": "devops"},
  {"question": "What are the key metrics for DevOps monitoring?", "intent": "devops"},
  {"question": "How can I implement blue-green deployment?", "intent": "devops"},
  {"question": "What's the difference between Ansible and Terraform?", "intent": "devops"},
  {"question": "How do I manage secrets in a CI/CD pipeline?", "intent": "devops"},
  {"question": "What are the benefits of containerization?", "intent": "devops"},
  {"question": "How can I implement canary releases?", "intent": "devops"},
  {"question": "What's the role of configuration management?", "intent": "devops"},
  {"question": "How do I set up monitoring and alerting?", "intent": "devops"},
  {"question": "What are GitOps best practices?", "intent": "devops"},

  {"question": "How do neural networks learn from data?", "intent": "ai_ml"},
  {"question": "What's the difference between supervised and unsupervised learning?", "intent": "ai_ml"},
  {"question": "How can I prevent overfitting in my model?", "intent": "ai_ml"},
  {"question": "What are the applications of natural language processing?", "intent": "ai_ml"},
  {"question": "How do I choose the right machine learning algorithm?", "intent": "ai_ml"},
  {"question": "What's the difference between precision and recall?", "intent": "ai_ml"},
  {"question": "How can I handle imbalanced datasets?", "intent": "ai_ml"},
  {"question": "What are convolutional neural networks used for?", "intent": "ai_ml"},
  {"question": "How do I evaluate model performance?", "intent": "ai_ml"},
  {"question": "What's the purpose of feature engineering?", "intent": "ai_ml"},
  {"question": "How can I implement transfer learning?", "intent": "ai_ml"},
  {"question": "What are gradient descent optimization techniques?", "intent": "ai_ml"},
  {"question": "How do I preprocess data for machine learning?", "intent": "ai_ml"},
  {"question": "What's the difference between AI and machine learning?", "intent": "ai_ml"},
  {"question": "How can I deploy a machine learning model to production?", "intent": "ai_ml"},

  {"question": "What programming language should I learn first?", "intent": "general"},
  {"question": "How can I improve my coding skills?", "intent": "general"},
  {"question": "What career paths are available in tech?", "intent": "general"},
  {"question": "How do I prepare for technical interviews?", "intent": "general"},
  {"question": "What's the best way to learn new technologies?", "intent": "general"},
  {"question": "How can I contribute to open source projects?", "intent": "general"},
  {"question": "What certifications are valuable in IT?", "intent": "general"},
  {"question": "How do I stay updated with technology trends?", "intent": "general"},
  {"question": "What's the difference between frontend and backend development?", "intent": "general"},
  {"question": "How can I build a strong tech portfolio?", "intent": "general"},
  {"question": "What are the essential skills for software developers?", "intent": "general"},
  {"question": "How do I transition into a tech career?", "intent": "general"},
  {"question": "What resources are best for learning programming?", "intent": "general"},
  {"question": "How can I network in the tech industry?", "intent": "general"},
  {"question": "What's the typical salary range for IT professionals?", "intent": "general"},

  {"question": "How do I protect my network from cyber attacks?", "intent": "cybersecurity"},
  {"question": "What's the difference between encryption and hashing?", "intent": "cybersecurity"},
  {"question": "How can I detect malware on my system?", "intent": "cybersecurity"},
  {"question": "What are common web application vulnerabilities?", "intent": "cybersecurity"},
  {"question": "How do I implement multi-factor authentication?", "intent": "cybersecurity"},
  {"question": "What's the purpose of a firewall?", "intent": "cybersecurity"},
  {"question": "How can I secure API endpoints?", "intent": "cybersecurity"},
  {"question": "What are SQL injection attacks and how do I prevent them?", "intent": "cybersecurity"},
  {"question": "How do I conduct a security audit?", "intent": "cybersecurity"},
  {"question": "What's the difference between symmetric and asymmetric encryption?", "intent": "cybersecurity"},
  {"question": "How can I implement zero trust security?", "intent": "cybersecurity"},
  {"question": "What are penetration testing methodologies?", "intent": "cybersecurity"},
  {"question": "How do I respond to a data breach?", "intent": "cybersecurity"},
  {"question": "What's the role of VPNs in security?", "intent": "cybersecurity"},
  {"question": "How can I secure cloud infrastructure?", "intent": "cybersecurity"},
  {"question": "What are the OWASP Top 10 vulnerabilities?", "intent": "cybersecurity"},
  {"question": "How do I implement secure coding practices?", "intent": "cybersecurity"},
  {"question": "What's the difference between IDS and IPS?", "intent": "cybersecurity"},
  {"question": "How can I protect against DDoS attacks?", "intent": "cybersecurity"},
  {"question": "What are security information and event management systems?", "intent": "cybersecurity"},

  {"question": "How do I design a scalable database schema?", "intent": "database"},
  {"question": "What's the difference between SQL and NoSQL databases?", "intent": "database"},
  {"question": "How can I optimize database performance?", "intent": "database"},
  {"question": "What are database indexing strategies?", "intent": "database"},
  {"question": "How do I implement database replication?", "intent": "database"},
  {"question": "What's the purpose of database normalization?", "intent": "database"},
  {"question": "How can I ensure database consistency?", "intent": "database"},
  {"question": "What are ACID properties in databases?", "intent": "database"},
  {"question": "How do I backup and restore databases?", "intent": "database"},
  {"question": "What's the difference between clustered and non-clustered indexes?", "intent": "database"},
  {"question": "How can I handle database migrations?", "intent": "database"},
  {"question": "What are stored procedures and when should I use them?", "intent": "database"},
  {"question": "How do I implement database sharding?", "intent": "database"},
  {"question": "What's the difference between OLTP and OLAP?", "intent": "database"},
  {"question": "How can I monitor database performance?", "intent": "database"},

  {"question": "How do I configure a router for optimal performance?", "intent": "networking"},
  {"question": "What's the difference between TCP and UDP?", "intent": "networking"},
  {"question": "How can I troubleshoot network connectivity issues?", "intent": "networking"},
  {"question": "What are the layers of the OSI model?", "intent": "networking"},
  {"question": "How do I set up a local area network?", "intent": "networking"},
  {"question": "What's the purpose of DNS servers?", "intent": "networking"},
  {"question": "How can I improve network security?", "intent": "networking"},
  {"question": "What are VLANs and how do they work?", "intent": "networking"},
  {"question": "How do I configure load balancing?", "intent": "networking"},
  {"question": "What's the difference between static and dynamic routing?", "intent": "networking"},
  {"question": "How can I monitor network traffic?", "intent": "networking"},
  {"question": "What are subnet masks and how do I calculate them?", "intent": "networking"},
  {"question": "How do I implement Quality of Service on my network?", "intent": "networking"},
  {"question": "What's the role of switches in networking?", "intent": "networking"},
  {"question": "How can I set up a wireless network securely?", "intent": "networking"},

  {"question": "How do I build a mobile app from scratch?", "intent": "mobile_development"},
  {"question": "What's the difference between native and hybrid apps?", "intent": "mobile_development"},
  {"question": "How can I optimize mobile app performance?", "intent": "mobile_development"},
  {"question": "What are the best practices for mobile UI design?", "intent": "mobile_development"},
  {"question": "How do I implement push notifications?", "intent": "mobile_development"},
  {"question": "What's the difference between iOS and Android development?", "intent": "mobile_development"},
  {"question": "How can I test mobile applications effectively?", "intent": "mobile_development"},
  {"question": "What are cross-platform development frameworks?", "intent": "mobile_development"},
  {"question": "How do I handle offline functionality in mobile apps?", "intent": "mobile_development"},
  {"question": "What's the purpose of mobile app analytics?", "intent": "mobile_development"},
  {"question": "How can I monetize my mobile application?", "intent": "mobile_development"},
  {"question": "What are progressive web apps?", "intent": "mobile_development"},
  {"question": "How do I optimize battery usage in mobile apps?", "intent": "mobile_development"},
  {"question": "What's the app store submission process?", "intent": "mobile_development"},
  {"question": "How can I implement in-app purchases?", "intent": "mobile_development"},

  {"question": "How do I create responsive web designs?", "intent": "web_development"},
  {"question": "What's the difference between HTML5 and previous versions?", "intent": "web_development"},
  {"question": "How can I improve website loading speed?", "intent": "web_development"},
  {"question": "What are JavaScript frameworks and which should I use?", "intent": "web_development"},
  {"question": "How do I implement SEO best practices?", "intent": "web_development"},
  {"question": "What's the purpose of CSS preprocessors?", "intent": "web_development"},
  {"question": "How can I make my website accessible?", "intent": "web_development"},
  {"question": "What are single-page applications?", "intent": "web_development"},
  {"question": "How do I handle cross-browser compatibility?", "intent": "web_development"},
  {"question": "What's the difference between cookies and local storage?", "intent": "web_development"},
  {"question": "How can I implement authentication in web apps?", "intent": "web_development"},
  {"question": "What are web components?", "intent": "web_development"},
  {"question": "How do I optimize images for the web?", "intent": "web_development"},
  {"question": "What's the role of webpack in web development?", "intent": "web_development"},
  {"question": "How can I implement real-time features using WebSockets?", "intent": "web_development"},

  {"question": "How do I analyze big data efficiently?", "intent": "data_science"},
  {"question": "What's the difference between data mining and data analysis?", "intent": "data_science"},
  {"question": "How can I visualize complex datasets?", "intent": "data_science"},
  {"question": "What are the best tools for data science?", "intent": "data_science"},
  {"question": "How do I clean and prepare data for analysis?", "intent": "data_science"},
  {"question": "What's the purpose of exploratory data analysis?", "intent": "data_science"},
  {"question": "How can I perform statistical testing?", "intent": "data_science"},
  {"question": "What are data pipelines and how do I build them?", "intent": "data_science"},
  {"question": "How do I work with time series data?", "intent": "data_science"},
  {"question": "What's the difference between correlation and causation?", "intent": "data_science"},
  {"question": "How can I handle missing data in datasets?", "intent": "data_science"},
  {"question": "What are data warehousing concepts?", "intent": "data_science"},
  {"question": "How do I perform A/B testing?", "intent": "data_science"},
  {"question": "What's the role of Python in data science?", "intent": "data_science"},
  {"question": "How can I create interactive dashboards?", "intent": "data_science"},

  {"question": "How do I implement blockchain technology?", "intent": "blockchain"},
  {"question": "What's the difference between Bitcoin and Ethereum?", "intent": "blockchain"},
  {"question": "How can I create a smart contract?", "intent": "blockchain"},
  {"question": "What are consensus mechanisms in blockchain?", "intent": "blockchain"},
  {"question": "How do I secure cryptocurrency wallets?", "intent": "blockchain"},
  {"question": "What's the purpose of mining in blockchain?", "intent": "blockchain"},
  {"question": "How can I build a decentralized application?", "intent": "blockchain"},
  {"question": "What are NFTs and how do they work?", "intent": "blockchain"},
  {"question": "How do I audit smart contracts for security?", "intent": "blockchain"},
  {"question": "What's the difference between public and private blockchains?", "intent": "blockchain"},

  {"question": "How do I set up a virtual reality development environment?", "intent": "emerging_tech"},
  {"question": "What's the difference between AR and VR?", "intent": "emerging_tech"},
  {"question": "How can I develop for IoT devices?", "intent": "emerging_tech"},
  {"question": "What are quantum computing applications?", "intent": "emerging_tech"},
  {"question": "How do I work with edge computing?", "intent": "emerging_tech"},
  {"question": "What's the future of 5G technology?", "intent": "emerging_tech"},
  {"question": "How can I implement computer vision systems?", "intent": "emerging_tech"},
  {"question": "What are digital twins in technology?", "intent": "emerging_tech"},
  {"question": "How do I develop voice-enabled applications?", "intent": "emerging_tech"},
  {"question": "What's the role of robotics in modern computing?", "intent": "emerging_tech"},

  {"question": "How do I manage an IT project effectively?", "intent": "it_management"},
  {"question": "What's the difference between Agile and Waterfall?", "intent": "it_management"},
  {"question": "How can I estimate software development costs?", "intent": "it_management"},
  {"question": "What are IT governance best practices?", "intent": "it_management"},
  {"question": "How do I conduct sprint planning meetings?", "intent": "it_management"},
  {"question": "What's the purpose of IT service management?", "intent": "it_management"},
  {"question": "How can I improve team collaboration in tech projects?", "intent": "it_management"},
  {"question": "What are key performance indicators for IT?", "intent": "it_management"},
  {"question": "How do I handle technical debt?", "intent": "it_management"},
  {"question": "What's the role of a Scrum Master?", "intent": "it_management"},
  {"question": "How can I implement change management in IT?", "intent": "it_management"},
  {"question": "What are IT compliance requirements?", "intent": "it_management"},
  {"question": "How do I create technical documentation?", "intent": "it_management"},
  {"question": "What's the difference between product and project management?", "intent": "it_management"},
  {"question": "How can I manage remote development teams?", "intent": "it_management"},

  {"question": "How do I choose the right operating system?", "intent": "systems"},
  {"question": "What's the difference between processes and threads?", "intent": "systems"},
  {"question": "How can I optimize system performance?", "intent": "systems"},
  {"question": "What are virtualization technologies?", "intent": "systems"},
  {"question": "How do I troubleshoot system crashes?", "intent": "systems"},
  {"question": "What's the purpose of system calls?", "intent": "systems"},
  {"question": "How can I manage system resources efficiently?", "intent": "systems"},
  {"question": "What are the components of an operating system?", "intent": "systems"},
  {"question": "How do I implement system monitoring?", "intent": "systems"},
  {"question": "What's the difference between 32-bit and 64-bit systems?", "intent": "systems"},
  {"question": "How can I automate system administration tasks?", "intent": "systems"},
  {"question": "What are containerization benefits for systems?", "intent": "systems"},
  {"question": "How do I configure system security policies?", "intent": "systems"},
  {"question": "What's the role of kernel in operating systems?", "intent": "systems"},
  {"question": "How can I recover from system failures?", "intent": "systems"}
]